django_jwt/__init__.py
django_jwt/backends.py
django_jwt/compat.py
django_jwt/decorators.py
django_jwt/exceptions.py
django_jwt/locale/ar/LC_MESSAGES/django.mo
django_jwt/locale/ar/LC_MESSAGES/django.po
django_jwt/locale/de/LC_MESSAGES/django.mo
django_jwt/locale/de/LC_MESSAGES/django.po
django_jwt/locale/es/LC_MESSAGES/django.mo
django_jwt/locale/es/LC_MESSAGES/django.po
django_jwt/locale/fr/LC_MESSAGES/django.mo
django_jwt/locale/fr/LC_MESSAGES/django.po
django_jwt/locale/nl/LC_MESSAGES/django.mo
django_jwt/locale/nl/LC_MESSAGES/django.po
django_jwt/locale/pt_BR/LC_MESSAGES/django.mo
django_jwt/locale/pt_BR/LC_MESSAGES/django.po
django_jwt/locale/zh_Hans/LC_MESSAGES/django.po
django_jwt/middleware.py
django_jwt/mixins.py
django_jwt/mutations.py
django_jwt/path.py
django_jwt/refresh_token/__init__.py
django_jwt/refresh_token/admin/__init__.py
django_jwt/refresh_token/admin/filters.py
django_jwt/refresh_token/apps.py
django_jwt/refresh_token/decorators.py
django_jwt/refresh_token/locale/ar/LC_MESSAGES/django.mo
django_jwt/refresh_token/locale/ar/LC_MESSAGES/django.po
django_jwt/refresh_token/locale/es/LC_MESSAGES/django.mo
django_jwt/refresh_token/locale/es/LC_MESSAGES/django.po
django_jwt/refresh_token/locale/fr/LC_MESSAGES/django.mo
django_jwt/refresh_token/locale/fr/LC_MESSAGES/django.po
django_jwt/refresh_token/locale/nl/LC_MESSAGES/django.mo
django_jwt/refresh_token/locale/nl/LC_MESSAGES/django.po
django_jwt/refresh_token/locale/pt_BR/LC_MESSAGES/django.mo
django_jwt/refresh_token/locale/pt_BR/LC_MESSAGES/django.po
django_jwt/refresh_token/locale/zh_Hans/LC_MESSAGES/django.po
django_jwt/refresh_token/management/__init__.py
django_jwt/refresh_token/management/commands/__init__.py
django_jwt/refresh_token/management/commands/cleartokens.py
django_jwt/refresh_token/managers.py
django_jwt/refresh_token/migrations/0001_initial.py
django_jwt/refresh_token/migrations/0002_auto_20190130_0900.py
django_jwt/refresh_token/migrations/__init__.py
weenspace_django_jwt-1.0.1.dist-info/LICENSE
weenspace_django_jwt-1.0.1.dist-info/METADATA
weenspace_django_jwt-1.0.1.dist-info/WHEEL
weenspace_django_jwt-1.0.1.dist-info/RECORD
