Metadata-Version: 2.1
Name: weenspace-django-jwt
Version: 1.0.1
Summary: JSON Web Token for Django REST and GraphQL.
Home-page: https://github.com/WeenSpace/weenspacce-django-jwt
License: MIT
Keywords: django,jwt,API,REST,GraphQL
Author: Huynh Doan Thinh
Author-email: hdthinh@gmail.com
Requires-Python: >=3.10.0,<4.0.0
Classifier: License :: OSI Approved :: MIT License
Classifier: Programming Language :: Python :: 3
Classifier: Programming Language :: Python :: 3.10
Classifier: Programming Language :: Python :: 3.11
Requires-Dist: Django (>=4.0.0)
Requires-Dist: PyJWT (>=2,<3)
Requires-Dist: graphene (>=2.1.5)
Requires-Dist: graphene-django (>=2.0.0)
Project-URL: Documentation, https://github.com/WeenSpace/weenspacce-django-jwt
Project-URL: Repository, https://github.com/WeenSpace/weenspacce-django-jwt
